{
    "@text": "What is portrayed by track list of Morning Musume no Hyokkori Hy\u014dtanjima ?",
    "@confidence": "0.5",
    "@support": "0",
    "@types": "",
    "@sparql": "",
    "@policy": "whitelist",
    "Resources": [
        {
            "@URI": "http://dbpedia.org/resource/Morning_Musume",
            "@support": "1315",
            "@types": "Wikidata:Q43229,Wikidata:Q24229398,Wikidata:Q215380,DUL:SocialPerson,DUL:Agent,Schema:Organization,Schema:MusicGroup,DBpedia:Organisation,DBpedia:Group,DBpedia:Band,DBpedia:Agent",
            "@surfaceForm": "Morning Musume",
            "@offset": "35",
            "@similarityScore": "1.0",
            "@percentageOfSecondRank": "0.0"
        }
    ]
}