{
    "@text": "Which field of study involves the history of mathematics?",
    "@confidence": "0.5",
    "@support": "0",
    "@types": "",
    "@sparql": "",
    "@policy": "whitelist",
    "Resources": [
        {
            "@URI": "http://dbpedia.org/resource/Mathematics",
            "@support": "27468",
            "@types": "",
            "@surfaceForm": "mathematics",
            "@offset": "45",
            "@similarityScore": "0.9996456934416806",
            "@percentageOfSecondRank": "2.1411442224367197E-4"
        }
    ]
}