{
    "@text": "What is the diplomatic relation between Iceland, which has arrondissements, and Arkhangelsk Oblast?",
    "@confidence": "0.5",
    "@support": "0",
    "@types": "",
    "@sparql": "",
    "@policy": "whitelist",
    "Resources": [
        {
            "@URI": "http://dbpedia.org/resource/Iceland",
            "@support": "23121",
            "@types": "Wikidata:Q6256,Schema:Place,Schema:Country,DBpedia:PopulatedPlace,DBpedia:Place,DBpedia:Location,DBpedia:Country",
            "@surfaceForm": "Iceland",
            "@offset": "40",
            "@similarityScore": "0.9996814935904526",
            "@percentageOfSecondRank": "1.6821977440446256E-4"
        },
        {
            "@URI": "http://dbpedia.org/resource/Arrondissements_of_France",
            "@support": "2109",
            "@types": "",
            "@surfaceForm": "arrondissements",
            "@offset": "59",
            "@similarityScore": "0.950952651114578",
            "@percentageOfSecondRank": "0.027249535452578216"
        },
        {
            "@URI": "http://dbpedia.org/resource/Arkhangelsk",
            "@support": "1826",
            "@types": "Wikidata:Q486972,Schema:Place,DBpedia:Settlement,DBpedia:PopulatedPlace,DBpedia:Place,DBpedia:Location",
            "@surfaceForm": "Arkhangelsk",
            "@offset": "80",
            "@similarityScore": "0.9705041467333749",
            "@percentageOfSecondRank": "0.029648701867589656"
        }
    ]
}